py_jwt_validator/__init__.py
py_jwt_validator/jwk/__init__.py
py_jwt_validator/jws/__init__.py
py_jwt_validator/utils/__init__.py
py_jwt_validator-0.6.0.dist-info/LICENSE
py_jwt_validator-0.6.0.dist-info/METADATA
py_jwt_validator-0.6.0.dist-info/WHEEL
py_jwt_validator-0.6.0.dist-info/top_level.txt
py_jwt_validator-0.6.0.dist-info/RECORD
