Metadata-Version: 2.1
Name: py-jwt-validator
Version: 0.6.0
Summary: Python JWT Signature Validator - Asymetric Keys - From exponent and modulus
Home-page: https://github.com/adrianlzr/py-jwt-validator
Author: Adrian Lazar
Author-email: adrian.lazar95@outlook.com
License: MIT
Project-URL: Documentation & Source, https://github.com/adrianlzr/py-jwt-validator
Project-URL: Issue Tracker, https://github.com/adrianlzr/py-jwt-validator/issues
Keywords: jwt jwt-validator python-jwt-valdidator jwt-signature signature jwt-signature-validator
Platform: UNKNOWN
Classifier: Programming Language :: Python :: 3
Classifier: License :: OSI Approved :: MIT License
Classifier: Operating System :: OS Independent
Classifier: Development Status :: 5 - Production/Stable
Classifier: Topic :: Security :: Cryptography 
Requires-Python: >=3
Requires-Dist: six
Requires-Dist: requests
Requires-Dist: requests-cache
